litchat/__about__.py
litchat/__init__.py
litchat/__main__.py
litchat/cli/__init__.py
litchat-0.0.1.dist-info/METADATA
litchat-0.0.1.dist-info/WHEEL
litchat-0.0.1.dist-info/entry_points.txt
litchat-0.0.1.dist-info/licenses/LICENSE.txt
litchat-0.0.1.dist-info/RECORD
